Metadata-Version: 1.1
Name: django-productline
Version: 0.3
Summary: an approach to feature-oriented software development(FOSD) of web application product lines based on django
Home-page: https://github.com/henzk/django-productline
Author: Hendrik Speidel
Author-email: hendrik@schnapptack.de
License: The MIT License
Keywords: django,FOSD,FOP,feature-oriented-programming,product-line,web-application
Platform: UNKNOWN
Classifier: License :: OSI Approved :: MIT License
Classifier: Programming Language :: Python
Classifier: Environment :: Web Environment
Classifier: Framework :: Django
Classifier: Intended Audience :: Developers
Classifier: Operating System :: OS Independent
